competest/__init__.py
competest/competest.py
competest/linux.py
competest/parsers.py
competest/windows.py
competest/compilers/__init__.py
competest/compilers/compilers_common.py
competest/compilers/compilers_linux.py
competest/compilers/compilers_windows.py
competest-0.0.12.dist-info/LICENSE
competest-0.0.12.dist-info/METADATA
competest-0.0.12.dist-info/WHEEL
competest-0.0.12.dist-info/entry_points.txt
competest-0.0.12.dist-info/top_level.txt
competest-0.0.12.dist-info/RECORD
