Metadata-Version: 2.1
Name: competest
Version: 0.0.12
Summary: A python cli tool to test competitive programming solutions(code) against multiple test cases and measure execution time.
Home-page: https://github.com/shaileshaanand/competester
Author: Shailesh Aanand
Author-email: anaandshailu@gmail.com
License: GPL-3.0 License
Keywords: competitive-programming,testing,coding
Platform: UNKNOWN
Requires-Python: >=3.7
Requires-Dist: Click
